argonctl/__init__.py
argonctl/cli/__init__.py
argonctl/cli/main.py
argonctl/core/__init__.py
argonctl/core/branch_manager.py
argonctl/core/db_utils.py
argonctl/core/docker_utils.py
argonctl/core/metadata.py
argonctl/core/s3_utils.py
argonctl/core/setup_utils.py
argonctl/core/test_core.py
argonctl-0.1.2.dist-info/licenses/LICENSE
argonctl-0.1.2.dist-info/METADATA
argonctl-0.1.2.dist-info/WHEEL
argonctl-0.1.2.dist-info/entry_points.txt
argonctl-0.1.2.dist-info/top_level.txt
argonctl-0.1.2.dist-info/RECORD
