Metadata-Version: 2.4
Name: argonctl
Version: 0.1.2
Summary: Argon CLI brings Git-style branching to MongoDB, streamlining AI, ML, and data science project management.
Author-email: Jake Wang <jake.wang@argonlabs.tech>
License-Expression: MIT
Project-URL: Homepage, https://github.com/argon-lab/argon
Project-URL: Bug Tracker, https://github.com/argon-lab/argon/issues
Keywords: mongodb,data-science,branching,version-control,database
Classifier: Development Status :: 4 - Beta
Classifier: Environment :: Console
Classifier: Intended Audience :: Developers
Classifier: Intended Audience :: Science/Research
Classifier: Operating System :: OS Independent
Classifier: Programming Language :: Python :: 3
Classifier: Programming Language :: Python :: 3.8
Classifier: Programming Language :: Python :: 3.9
Classifier: Programming Language :: Python :: 3.10
Classifier: Programming Language :: Python :: 3.11
Classifier: Topic :: Database
Classifier: Topic :: Scientific/Engineering :: Artificial Intelligence
Classifier: Topic :: Software Development :: Version Control
Requires-Python: >=3.8
License-File: LICENSE
Requires-Dist: boto3>=1.26.0
Requires-Dist: python-dotenv>=0.19.0
Requires-Dist: docker>=6.1.0
Requires-Dist: typer[all]>=0.9.0
Requires-Dist: fastapi>=0.100.0
Requires-Dist: uvicorn>=0.22.0
Requires-Dist: jinja2>=3.1.0
Requires-Dist: rich>=13.0.0
Dynamic: license-file
